sonyci-0.3.0.dist-info/METADATA
sonyci-0.3.0.dist-info/WHEEL
sonyci-0.3.0.dist-info/entry_points.txt
sonyci-0.3.0.dist-info/licenses/LICENSE
sonyci/__init__.py
sonyci/__main__.py
sonyci/_version.py
sonyci/cli.py
sonyci/config.py
sonyci/log.py
sonyci/sonyci.py
sonyci/types.py
sonyci/utils.py
sonyci-0.3.0.dist-info/RECORD
