Metadata-Version: 2.1
Name: sonyci
Version: 0.3.0
Summary: A Sony Ci api client
Author-Email: WGBH-MLA <ryan_harbert@wgbh.org>
License: MIT
Requires-Python: >=3.8
Requires-Dist: pydantic~=2.9
Requires-Dist: requests-oauth2client~=1.6
Requires-Dist: loguru~=0.7
Provides-Extra: test
Requires-Dist: pytest~=8.3; extra == "test"
Requires-Dist: vcrpy~=6.0; extra == "test"
Requires-Dist: pytest-vcr~=1.0; extra == "test"
Requires-Dist: pytest-cov~=5.0; extra == "test"
Requires-Dist: pytest-sugar~=1.0; extra == "test"
Requires-Dist: pytest-xdist~=3.6; extra == "test"
Requires-Dist: urllib3~=1.26; extra == "test"
Provides-Extra: cli
Requires-Dist: typer[all]~=0.12; extra == "cli"
Provides-Extra: cli-ci
Requires-Dist: typer~=0.12; extra == "cli-ci"
Provides-Extra: tui
Requires-Dist: trogon~=0.5; extra == "tui"
Provides-Extra: docs
Requires-Dist: mkdocs~=1.6; extra == "docs"
Requires-Dist: mkdocs-material~=9.5; extra == "docs"
Requires-Dist: mkdocs-git-revision-date-localized-plugin~=1.2; extra == "docs"
Requires-Dist: mike~=2.1; extra == "docs"
Requires-Dist: mkdocstrings[python]~=0.26; extra == "docs"
Requires-Dist: mkdocs-jupyter~=0.24; extra == "docs"
